hackathon_evaluation_rag/__init__.py
hackathon_evaluation_rag/config.py
hackathon_evaluation_rag/evaluate.py
hackathon_evaluation_rag/llm.py
hackathon_evaluation_rag/load.py
hackathon_evaluation_rag/main.py
hackathon_evaluation_rag/results.py
hackathon_evaluation_rag-0.1.3.dist-info/METADATA
hackathon_evaluation_rag-0.1.3.dist-info/WHEEL
hackathon_evaluation_rag-0.1.3.dist-info/RECORD
